{
  "generatedAt": "2025-11-24T03:50:52.505Z",
  "node": "v20.19.2",
  "results": [
    {
      "size": 5000,
      "scenario": "S1",
      "label": "stream ON, cache OFF, chunk ON",
      "oneShotMs": 0.002008333333333212,
      "appendWorkloadMs": 1.7184583333333403,
      "lastMode": "chunked",
      "appendHits": 0,
      "chunkInfoOne": {
        "count": 4,
        "maxChunkChars": 8000,
        "maxChunkLines": 150
      },
      "chunkInfoAppendLast": {
        "count": 4,
        "maxChunkChars": 8000,
        "maxChunkLines": 150
      }
    },
    {
      "size": 5000,
      "scenario": "S2",
      "label": "stream ON, cache ON, chunk OFF",
      "oneShotMs": 0.0003708333333330908,
      "appendWorkloadMs": 0.40516700000000344,
      "lastMode": "append",
      "appendHits": 35,
      "chunkInfoOne": null,
      "chunkInfoAppendLast": null
    },
    {
      "size": 5000,
      "scenario": "S3",
      "label": "stream ON, cache ON, chunk ON",
      "oneShotMs": 0.00011386666666671394,
      "appendWorkloadMs": 0.33479116666666187,
      "lastMode": "append",
      "appendHits": 35,
      "chunkInfoOne": {
        "count": 1,
        "maxChunkChars": 8000,
        "maxChunkLines": 350
      },
      "chunkInfoAppendLast": {
        "count": 1,
        "maxChunkChars": 8000,
        "maxChunkLines": 350
      }
    },
    {
      "size": 5000,
      "scenario": "S4",
      "label": "stream OFF, chunk ON",
      "oneShotMs": 0.2226249999999998,
      "appendWorkloadMs": 0.45190349999999074,
      "lastMode": "idle",
      "appendHits": 0,
      "chunkInfoOne": {
        "count": 4,
        "maxChunkChars": 8000,
        "maxChunkLines": 150
      },
      "chunkInfoAppendLast": {
        "count": 4,
        "maxChunkChars": 8000,
        "maxChunkLines": 150
      }
    },
    {
      "size": 5000,
      "scenario": "S5",
      "label": "stream OFF, chunk OFF",
      "oneShotMs": 0.11992083333333312,
      "appendWorkloadMs": 0.4372776666666643,
      "lastMode": "idle",
      "appendHits": 0,
      "chunkInfoOne": null,
      "chunkInfoAppendLast": null
    },
    {
      "size": 5000,
      "scenario": "M1",
      "label": "markdown-it (baseline)",
      "oneShotMs": 0.40230416666666663,
      "appendWorkloadMs": 0.6251388333333358,
      "lastMode": "n/a",
      "appendHits": 0,
      "chunkInfoOne": null,
      "chunkInfoAppendLast": null
    },
    {
      "size": 5000,
      "scenario": "R1",
      "label": "remark (parse only)",
      "oneShotMs": 3.8699375,
      "appendWorkloadMs": 8.122055499999982,
      "lastMode": "n/a",
      "appendHits": 0,
      "chunkInfoOne": null,
      "chunkInfoAppendLast": null
    },
    {
      "size": 20000,
      "scenario": "S1",
      "label": "stream ON, cache OFF, chunk ON",
      "oneShotMs": 0.00022499999999752162,
      "appendWorkloadMs": 2.2963581999999976,
      "lastMode": "chunked",
      "appendHits": 0,
      "chunkInfoOne": {
        "count": 8,
        "maxChunkChars": 8000,
        "maxChunkLines": 233
      },
      "chunkInfoAppendLast": {
        "count": 8,
        "maxChunkChars": 8000,
        "maxChunkLines": 233
      }
    },
    {
      "size": 20000,
      "scenario": "S2",
      "label": "stream ON, cache ON, chunk OFF",
      "oneShotMs": 0.0001520999999996775,
      "appendWorkloadMs": 0.9363752000000091,
      "lastMode": "append",
      "appendHits": 30,
      "chunkInfoOne": null,
      "chunkInfoAppendLast": null
    },
    {
      "size": 20000,
      "scenario": "S3",
      "label": "stream ON, cache ON, chunk ON",
      "oneShotMs": 0.00012079999999912162,
      "appendWorkloadMs": 0.8692499999999314,
      "lastMode": "append",
      "appendHits": 30,
      "chunkInfoOne": {
        "count": 1,
        "maxChunkChars": 8000,
        "maxChunkLines": 350
      },
      "chunkInfoAppendLast": {
        "count": 1,
        "maxChunkChars": 8000,
        "maxChunkLines": 350
      }
    },
    {
      "size": 20000,
      "scenario": "S4",
      "label": "stream OFF, chunk ON",
      "oneShotMs": 0.6777791499999978,
      "appendWorkloadMs": 2.178266599999995,
      "lastMode": "idle",
      "appendHits": 0,
      "chunkInfoOne": {
        "count": 8,
        "maxChunkChars": 8000,
        "maxChunkLines": 233
      },
      "chunkInfoAppendLast": {
        "count": 8,
        "maxChunkChars": 8000,
        "maxChunkLines": 233
      }
    },
    {
      "size": 20000,
      "scenario": "S5",
      "label": "stream OFF, chunk OFF",
      "oneShotMs": 0.50873335,
      "appendWorkloadMs": 1.7427659999999832,
      "lastMode": "idle",
      "appendHits": 0,
      "chunkInfoOne": null,
      "chunkInfoAppendLast": null
    },
    {
      "size": 20000,
      "scenario": "M1",
      "label": "markdown-it (baseline)",
      "oneShotMs": 0.47767294999999876,
      "appendWorkloadMs": 1.5167910000000007,
      "lastMode": "n/a",
      "appendHits": 0,
      "chunkInfoOne": null,
      "chunkInfoAppendLast": null
    },
    {
      "size": 20000,
      "scenario": "R1",
      "label": "remark (parse only)",
      "oneShotMs": 16.5730104,
      "appendWorkloadMs": 51.24637520000003,
      "lastMode": "n/a",
      "appendHits": 0,
      "chunkInfoOne": null,
      "chunkInfoAppendLast": null
    },
    {
      "size": 50000,
      "scenario": "S1",
      "label": "stream ON, cache OFF, chunk ON",
      "oneShotMs": 0.0005374999999958163,
      "appendWorkloadMs": 5.77077050000014,
      "lastMode": "chunked",
      "appendHits": 0,
      "chunkInfoOne": {
        "count": 14,
        "maxChunkChars": 8000,
        "maxChunkLines": 350
      },
      "chunkInfoAppendLast": {
        "count": 14,
        "maxChunkChars": 8000,
        "maxChunkLines": 350
      }
    },
    {
      "size": 50000,
      "scenario": "S2",
      "label": "stream ON, cache ON, chunk OFF",
      "oneShotMs": 0.00020419999998466665,
      "appendWorkloadMs": 1.9126669999998853,
      "lastMode": "append",
      "appendHits": 25,
      "chunkInfoOne": null,
      "chunkInfoAppendLast": null
    },
    {
      "size": 50000,
      "scenario": "S3",
      "label": "stream ON, cache ON, chunk ON",
      "oneShotMs": 0.00016669999999976425,
      "appendWorkloadMs": 2.4397402500001135,
      "lastMode": "append",
      "appendHits": 25,
      "chunkInfoOne": {
        "count": 3,
        "maxChunkChars": 8000,
        "maxChunkLines": 350
      },
      "chunkInfoAppendLast": {
        "count": 3,
        "maxChunkChars": 8000,
        "maxChunkLines": 350
      }
    },
    {
      "size": 50000,
      "scenario": "S4",
      "label": "stream OFF, chunk ON",
      "oneShotMs": 1.8907999999999903,
      "appendWorkloadMs": 6.270041249999792,
      "lastMode": "idle",
      "appendHits": 0,
      "chunkInfoOne": {
        "count": 8,
        "maxChunkChars": 8000,
        "maxChunkLines": 350
      },
      "chunkInfoAppendLast": {
        "count": 8,
        "maxChunkChars": 8000,
        "maxChunkLines": 350
      }
    },
    {
      "size": 50000,
      "scenario": "S5",
      "label": "stream OFF, chunk OFF",
      "oneShotMs": 1.5608749999999874,
      "appendWorkloadMs": 4.952771749999897,
      "lastMode": "idle",
      "appendHits": 0,
      "chunkInfoOne": null,
      "chunkInfoAppendLast": null
    },
    {
      "size": 50000,
      "scenario": "M1",
      "label": "markdown-it (baseline)",
      "oneShotMs": 1.2720207999999957,
      "appendWorkloadMs": 4.228677249999919,
      "lastMode": "n/a",
      "appendHits": 0,
      "chunkInfoOne": null,
      "chunkInfoAppendLast": null
    },
    {
      "size": 50000,
      "scenario": "R1",
      "label": "remark (parse only)",
      "oneShotMs": 54.02084590000002,
      "appendWorkloadMs": 157.63122924999988,
      "lastMode": "n/a",
      "appendHits": 0,
      "chunkInfoOne": null,
      "chunkInfoAppendLast": null
    },
    {
      "size": 100000,
      "scenario": "S1",
      "label": "stream ON, cache OFF, chunk ON",
      "oneShotMs": 0.0014791666666648477,
      "appendWorkloadMs": 12.71388966666685,
      "lastMode": "chunked",
      "appendHits": 0,
      "chunkInfoOne": {
        "count": 27,
        "maxChunkChars": 12516,
        "maxChunkLines": 350
      },
      "chunkInfoAppendLast": {
        "count": 27,
        "maxChunkChars": 12516,
        "maxChunkLines": 350
      }
    },
    {
      "size": 100000,
      "scenario": "S2",
      "label": "stream ON, cache ON, chunk OFF",
      "oneShotMs": 0.0008819999999711096,
      "appendWorkloadMs": 4.127125333333727,
      "lastMode": "append",
      "appendHits": 20,
      "chunkInfoOne": null,
      "chunkInfoAppendLast": null
    },
    {
      "size": 100000,
      "scenario": "S3",
      "label": "stream ON, cache ON, chunk ON",
      "oneShotMs": 0.00029849999994742876,
      "appendWorkloadMs": 3.902319333333253,
      "lastMode": "append",
      "appendHits": 20,
      "chunkInfoOne": {
        "count": 5,
        "maxChunkChars": 8000,
        "maxChunkLines": 350
      },
      "chunkInfoAppendLast": {
        "count": 5,
        "maxChunkChars": 8000,
        "maxChunkLines": 350
      }
    },
    {
      "size": 100000,
      "scenario": "S4",
      "label": "stream OFF, chunk ON",
      "oneShotMs": 4.008124999999988,
      "appendWorkloadMs": 11.382263000000117,
      "lastMode": "idle",
      "appendHits": 0,
      "chunkInfoOne": {
        "count": 8,
        "maxChunkChars": 12516,
        "maxChunkLines": 350
      },
      "chunkInfoAppendLast": {
        "count": 8,
        "maxChunkChars": 12516,
        "maxChunkLines": 350
      }
    },
    {
      "size": 100000,
      "scenario": "S5",
      "label": "stream OFF, chunk OFF",
      "oneShotMs": 4.138131999999966,
      "appendWorkloadMs": 10.861403000000337,
      "lastMode": "idle",
      "appendHits": 0,
      "chunkInfoOne": null,
      "chunkInfoAppendLast": null
    },
    {
      "size": 100000,
      "scenario": "M1",
      "label": "markdown-it (baseline)",
      "oneShotMs": 3.043611166666627,
      "appendWorkloadMs": 7.736889000000247,
      "lastMode": "n/a",
      "appendHits": 0,
      "chunkInfoOne": null,
      "chunkInfoAppendLast": null
    },
    {
      "size": 100000,
      "scenario": "R1",
      "label": "remark (parse only)",
      "oneShotMs": 100.80052783333333,
      "appendWorkloadMs": 340.9677226666663,
      "lastMode": "n/a",
      "appendHits": 0,
      "chunkInfoOne": null,
      "chunkInfoAppendLast": null
    },
    {
      "size": 200000,
      "scenario": "S1",
      "label": "stream ON, cache OFF, chunk ON",
      "oneShotMs": 7.484958499999948,
      "appendWorkloadMs": 29.12072950000038,
      "lastMode": "full",
      "appendHits": 0,
      "chunkInfoOne": {
        "count": 26,
        "maxChunkChars": 12402,
        "maxChunkLines": 350
      },
      "chunkInfoAppendLast": {
        "count": 26,
        "maxChunkChars": 12402,
        "maxChunkLines": 350
      }
    },
    {
      "size": 200000,
      "scenario": "S2",
      "label": "stream ON, cache ON, chunk OFF",
      "oneShotMs": 8.854302000000189,
      "appendWorkloadMs": 15.04739600000039,
      "lastMode": "full",
      "appendHits": 12,
      "chunkInfoOne": null,
      "chunkInfoAppendLast": null
    },
    {
      "size": 200000,
      "scenario": "S3",
      "label": "stream ON, cache ON, chunk ON",
      "oneShotMs": 7.743479250000064,
      "appendWorkloadMs": 15.381667000001016,
      "lastMode": "chunked",
      "appendHits": 12,
      "chunkInfoOne": {
        "count": 53,
        "maxChunkChars": 25010,
        "maxChunkLines": 350
      },
      "chunkInfoAppendLast": {
        "count": 53,
        "maxChunkChars": 25010,
        "maxChunkLines": 350
      }
    },
    {
      "size": 200000,
      "scenario": "S4",
      "label": "stream OFF, chunk ON",
      "oneShotMs": 10.794468750000078,
      "appendWorkloadMs": 24.25079100000039,
      "lastMode": "idle",
      "appendHits": 0,
      "chunkInfoOne": {
        "count": 8,
        "maxChunkChars": 25010,
        "maxChunkLines": 350
      },
      "chunkInfoAppendLast": {
        "count": 8,
        "maxChunkChars": 25010,
        "maxChunkLines": 350
      }
    },
    {
      "size": 200000,
      "scenario": "S5",
      "label": "stream OFF, chunk OFF",
      "oneShotMs": 7.525739749999957,
      "appendWorkloadMs": 25.365334499999335,
      "lastMode": "idle",
      "appendHits": 0,
      "chunkInfoOne": null,
      "chunkInfoAppendLast": null
    },
    {
      "size": 200000,
      "scenario": "M1",
      "label": "markdown-it (baseline)",
      "oneShotMs": 8.937541499999952,
      "appendWorkloadMs": 20.248394500001268,
      "lastMode": "n/a",
      "appendHits": 0,
      "chunkInfoOne": null,
      "chunkInfoAppendLast": null
    },
    {
      "size": 200000,
      "scenario": "R1",
      "label": "remark (parse only)",
      "oneShotMs": 330.25655199999983,
      "appendWorkloadMs": 922.754977999999,
      "lastMode": "n/a",
      "appendHits": 0,
      "chunkInfoOne": null,
      "chunkInfoAppendLast": null
    }
  ],
  "coldHot": [
    {
      "size": 5000,
      "id": "TS",
      "label": "markdown-it-ts (stream+chunk)",
      "type": "ts",
      "coldMs": 0.1696250000004511,
      "hotMs": 0.1134874999999738
    },
    {
      "size": 5000,
      "id": "MD",
      "label": "markdown-it (baseline)",
      "type": "md-original",
      "coldMs": 0.21958400000039546,
      "hotMs": 0.10553749999999126
    },
    {
      "size": 5000,
      "id": "RM",
      "label": "remark (parse only)",
      "type": "remark",
      "coldMs": 3.0711670000000595,
      "hotMs": 2.6144249999999376
    },
    {
      "size": 20000,
      "id": "TS",
      "label": "markdown-it-ts (stream+chunk)",
      "type": "ts",
      "coldMs": 0.9236670000009326,
      "hotMs": 0.5251374999999825
    },
    {
      "size": 20000,
      "id": "MD",
      "label": "markdown-it (baseline)",
      "type": "md-original",
      "coldMs": 0.9856249999993452,
      "hotMs": 0.4656624999999622
    },
    {
      "size": 20000,
      "id": "RM",
      "label": "remark (parse only)",
      "type": "remark",
      "coldMs": 13.042459000000235,
      "hotMs": 19.324012500000027
    },
    {
      "size": 50000,
      "id": "TS",
      "label": "markdown-it-ts (stream+chunk)",
      "type": "ts",
      "coldMs": 1.201375000000553,
      "hotMs": 1.5407416000000012
    },
    {
      "size": 50000,
      "id": "MD",
      "label": "markdown-it (baseline)",
      "type": "md-original",
      "coldMs": 1.0742090000003373,
      "hotMs": 1.1976416999999855
    },
    {
      "size": 50000,
      "id": "RM",
      "label": "remark (parse only)",
      "type": "remark",
      "coldMs": 52.00404200000048,
      "hotMs": 46.24202920000007
    },
    {
      "size": 100000,
      "id": "TS",
      "label": "markdown-it-ts (stream+chunk)",
      "type": "ts",
      "coldMs": 2.4729999999999563,
      "hotMs": 4.070679200000086
    },
    {
      "size": 100000,
      "id": "MD",
      "label": "markdown-it (baseline)",
      "type": "md-original",
      "coldMs": 2.1867910000000848,
      "hotMs": 2.98861250000009
    },
    {
      "size": 100000,
      "id": "RM",
      "label": "remark (parse only)",
      "type": "remark",
      "coldMs": 138.789166999999,
      "hotMs": 98.78394589999989
    }
  ]
}
